statease/__init__.py
statease/analysis.py
statease/client.py
statease/factor.py
statease/graph.py
statease/information.py
statease/node.py
statease/optimizer.py
statease/response.py
statease/row_status.py
statease/transform.py
statease-0.3.0.dist-info/LICENSE
statease-0.3.0.dist-info/METADATA
statease-0.3.0.dist-info/WHEEL
statease-0.3.0.dist-info/top_level.txt
statease-0.3.0.dist-info/RECORD
